{
  "data": [
    {
      "activeContentFileId": null,
      "activeContentHash": null,
      "activeContentPath": null,
      "activeContentSignedStatus": "unsigned",
      "activeContentType": "FILE",
      "agentDomain": "AD",
      "agentGroupId": "1022424678582482088",
      "agentId": "1036163683371316806",
      "agentInfected": false,
      "agentIp": "172.31.18.165",
      "agentIsActive": true,
      "agentIsDecommissioned": false,
      "agentMachineType": "laptop",
      "agentName": "F5310-285NXT2-L",
      "agentNetworkStatus": "connected",
      "agentOs": "windows",
      "agentTimestamp": "2021-12-12T13:50:42.011Z",
      "agentUuid": "f679d7b3265a46fc8cbc73f39cbf1107",
      "agentVersion": "21.6.4.423",
      "childProcCount": "28",
      "createdAt": "2021-12-12T13:50:42.011000Z",
      "crossProcCount": "986",
      "crossProcDupRemoteProcHandleCount": "964",
      "crossProcDupThreadHandleCount": "22",
      "crossProcOpenProcCount": "0",
      "crossProcOutOfStorylineCount": "0",
      "crossProcThreadCreateCount": "0",
      "dnsCount": "0",
      "endpointMachineType": "laptop",
      "endpointName": "F5310-285NXT2-L",
      "endpointOs": "windows",
      "eventIndex": "568",
      "eventTime": "2021-12-12T13:50:42.011Z",
      "eventType": "Not Reported",
      "fileIsExecutable": "True",
      "fileMd5": "1f8a0a7ed17e8f628598939dcaaa354e",
      "fileSha256": "196fc80802c7a409e92736de0f4c056d4d504df3ce4b0ac17ac3176b535171ed",
      "id": "631543045116919814",
      "indicatorBootConfigurationUpdateCount": "0",
      "indicatorEvasionCount": "22",
      "indicatorExploitationCount": "1",
      "indicatorGeneralCount": "0",
      "indicatorInfostealerCount": "0",
      "indicatorInjectionCount": "0",
      "indicatorPersistenceCount": "0",
      "indicatorPostExploitationCount": "0",
      "indicatorRansomwareCount": "0",
      "indicatorReconnaissanceCount": "0",
      "metaEventName": "HTTP",
      "moduleCount": "253",
      "netConnCount": "0",
      "netConnInCount": "0",
      "netConnOutCount": "0",
      "networkMethod": null,
      "networkSource": "CHROME",
      "networkUrl": "https://hq-logger01.gdit.com/logger/search.ftl?ehr=1&ausm_query=%2245.137.155.55/ex.sh%22%20OR%20%2245.137.155.55/kinsing%22%20OR%20%2280.71.158.12/libsystem.so%22%20OR%20%2280.71.158.12/kinsing%22%20OR%20%2280.71.158.12/Exploit69ogQNSQYz.class%22&from=$CurrentMonth&to=$Now&search_time=received_time",
      "objectType": "url",
      "parentPid": "18184",
      "parentProcessName": "old_chrome.exe",
      "parentProcessStartTime": "2021-12-12T13:49:34.015Z",
      "parentProcessUniqueKey": "F9317943001DB445",
      "pid": "20888",
      "processCmd": "\"C:\\Program Files (x86)\\Google\\Chrome\\Application\\chrome.exe\" --origin-trial-disabled-features=CaptureHandle --restore-last-session --flag-switches-begin --flag-switches-end",
      "processDisplayName": "Google Chrome",
      "processGroupId": "23A168D9150068D0",
      "processImagePath": "C:\\Program Files (x86)\\Google\\Chrome\\Application\\chrome.exe",
      "processImageSha1Hash": "84bc7424b07d5c3589317e5311e5ffaa60a38b62",
      "processIntegrityLevel": "MEDIUM",
      "processIsRedirectedCommandProcessor": "False",
      "processIsWow64": "False",
      "processName": "chrome.exe",
      "processRoot": "False",
      "processSessionId": "1",
      "processStartTime": "2021-12-12T13:49:41.897Z",
      "processSubSystem": "SYS_WIN32",
      "processUniqueKey": "F9317943001DB445",
      "publisher": "GOOGLE LLC",
      "registryChangeCount": "36",
      "relatedToThreat": "False",
      "rpid": null,
      "signatureSignedInvalidReason": null,
      "signedStatus": "signed",
      "siteId": "1015875214652745972",
      "siteName": "WinWStest",
      "srcProcActiveContentFileId": null,
      "srcProcActiveContentHash": null,
      "srcProcActiveContentPath": null,
      "srcProcActiveContentSignedStatus": "unsigned",
      "srcProcActiveContentType": "FILE",
      "srcProcBinaryisExecutable": "True",
      "srcProcCmdLine": "\"C:\\Program Files (x86)\\Google\\Chrome\\Application\\chrome.exe\" --origin-trial-disabled-features=CaptureHandle --restore-last-session --flag-switches-begin --flag-switches-end",
      "srcProcDisplayName": "Google Chrome",
      "srcProcImageMd5": "1f8a0a7ed17e8f628598939dcaaa354e",
      "srcProcImagePath": "C:\\Program Files (x86)\\Google\\Chrome\\Application\\chrome.exe",
      "srcProcImageSha1": "84bc7424b07d5c3589317e5311e5ffaa60a38b62",
      "srcProcImageSha256": "196fc80802c7a409e92736de0f4c056d4d504df3ce4b0ac17ac3176b535171ed",
      "srcProcIntegrityLevel": "MEDIUM",
      "srcProcIsNative64Bit": "False",
      "srcProcIsRedirectCmdProcessor": "False",
      "srcProcIsStorylineRoot": "False",
      "srcProcName": "chrome.exe",
      "srcProcParentImageMd5": "a98d71eb1bec5d38549b2155a3e54008",
      "srcProcParentImagePath": "C:\\Program Files (x86)\\Google\\Chrome\\Temp\\scoped_dir21036_1816210371\\old_chrome.exe",
      "srcProcParentImageSha1": "8bfc5af325534d4b4b690c4883e27e3d005eee20",
      "srcProcParentImageSha256": "e6d9df99f3bce911f8241e4e40784288b879b93feaeb5edddb1cb4e0cac675f8",
      "srcProcParentName": "old_chrome.exe",
      "srcProcParentPid": "18184",
      "srcProcParentProcUid": "61D32E0AAB0D437F",
      "srcProcParentStartTime": "2021-12-12T13:49:34.015Z",
      "srcProcParentUid": "61D32E0AAB0D437F",
      "srcProcPid": "20888",
      "srcProcPublisher": "GOOGLE LLC",
      "srcProcReasonSignatureInvalid": null,
      "srcProcRelatedToThreat": "False",
      "srcProcRpid": null,
      "srcProcSessionId": "1",
      "srcProcSignedStatus": "signed",
      "srcProcStartTime": "2021-12-12T13:49:41.897Z",
      "srcProcStorylineId": "23A168D9150068D0",
      "srcProcSubsystem": "SYS_WIN32",
      "srcProcTid": null,
      "srcProcUid": "F9317943001DB445",
      "srcProcUser": "AD\\Joshua.Vigil",
      "srcProcVerifiedStatus": "verified",
      "storyline": "23A168D9150068D0",
      "tgtFileCreationCount": "120",
      "tgtFileDeletionCount": "1232",
      "tgtFileModificationCount": "252",
      "tiOriginalEventId": null,
      "tiOriginalEventIndex": null,
      "tiOriginalEventTraceId": null,
      "tid": null,
      "tiindicatorRelatedEventTime": null,
      "traceId": "01FPQEJCXTB24VH4MZWMWNMC21",
      "trueContext": "23A168D9150068D0",
      "url": "https://hq-logger01.gdit.com/logger/search.ftl?ehr=1&ausm_query=%2245.137.155.55/ex.sh%22%20OR%20%2245.137.155.55/kinsing%22%20OR%20%2280.71.158.12/libsystem.so%22%20OR%20%2280.71.158.12/kinsing%22%20OR%20%2280.71.158.12/Exploit69ogQNSQYz.class%22&from=$CurrentMonth&to=$Now&search_time=received_time",
      "urlAction": null,
      "user": "AD\\Joshua.Vigil",
      "verifiedStatus": "verified"
    },
    {
      "activeContentFileId": null,
      "activeContentHash": null,
      "activeContentPath": null,
      "activeContentSignedStatus": "unsigned",
      "activeContentType": "FILE",
      "agentDomain": "AD",
      "agentGroupId": "1022424678582482088",
      "agentId": "1036163683371316806",
      "agentInfected": false,
      "agentIp": "172.31.18.165",
      "agentIsActive": true,
      "agentIsDecommissioned": false,
      "agentMachineType": "laptop",
      "agentName": "F5310-285NXT2-L",
      "agentNetworkStatus": "connected",
      "agentOs": "windows",
      "agentTimestamp": "2021-12-12T13:50:11.982Z",
      "agentUuid": "f679d7b3265a46fc8cbc73f39cbf1107",
      "agentVersion": "21.6.4.423",
      "childProcCount": "22",
      "createdAt": "2021-12-12T13:50:11.982000Z",
      "crossProcCount": "486",
      "crossProcDupRemoteProcHandleCount": "468",
      "crossProcDupThreadHandleCount": "18",
      "crossProcOpenProcCount": "0",
      "crossProcOutOfStorylineCount": "0",
      "crossProcThreadCreateCount": "0",
      "dnsCount": "0",
      "endpointMachineType": "laptop",
      "endpointName": "F5310-285NXT2-L",
      "endpointOs": "windows",
      "eventIndex": "401",
      "eventTime": "2021-12-12T13:50:11.982Z",
      "eventType": "Not Reported",
      "fileIsExecutable": "True",
      "fileMd5": "1f8a0a7ed17e8f628598939dcaaa354e",
      "fileSha256": "196fc80802c7a409e92736de0f4c056d4d504df3ce4b0ac17ac3176b535171ed",
      "id": "631543045037228032",
      "indicatorBootConfigurationUpdateCount": "0",
      "indicatorEvasionCount": "18",
      "indicatorExploitationCount": "1",
      "indicatorGeneralCount": "0",
      "indicatorInfostealerCount": "0",
      "indicatorInjectionCount": "0",
      "indicatorPersistenceCount": "0",
      "indicatorPostExploitationCount": "0",
      "indicatorRansomwareCount": "0",
      "indicatorReconnaissanceCount": "0",
      "metaEventName": "HTTP",
      "moduleCount": "253",
      "netConnCount": "0",
      "netConnInCount": "0",
      "netConnOutCount": "0",
      "networkMethod": null,
      "networkSource": "CHROME",
      "networkUrl": "https://hq-logger01.gdit.com/logger/search.ftl?ehr=1&ausm_query=%2245.137.155.55/ex.sh%22%20OR%20%2245.137.155.55/kinsing%22%20OR%20%2280.71.158.12/libsystem.so%22%20OR%20%2280.71.158.12/kinsing%22%20OR%20%2280.71.158.12/Exploit69ogQNSQYz.class%22&from=$CurrentMonth&to=$Now&search_time=received_time",
      "objectType": "url",
      "parentPid": "18184",
      "parentProcessName": "old_chrome.exe",
      "parentProcessStartTime": "2021-12-12T13:49:34.015Z",
      "parentProcessUniqueKey": "F9317943001DB445",
      "pid": "20888",
      "processCmd": "\"C:\\Program Files (x86)\\Google\\Chrome\\Application\\chrome.exe\" --origin-trial-disabled-features=CaptureHandle --restore-last-session --flag-switches-begin --flag-switches-end",
      "processDisplayName": "Google Chrome",
      "processGroupId": "23A168D9150068D0",
      "processImagePath": "C:\\Program Files (x86)\\Google\\Chrome\\Application\\chrome.exe",
      "processImageSha1Hash": "84bc7424b07d5c3589317e5311e5ffaa60a38b62",
      "processIntegrityLevel": "MEDIUM",
      "processIsRedirectedCommandProcessor": "False",
      "processIsWow64": "False",
      "processName": "chrome.exe",
      "processRoot": "False",
      "processSessionId": "1",
      "processStartTime": "2021-12-12T13:49:41.897Z",
      "processSubSystem": "SYS_WIN32",
      "processUniqueKey": "F9317943001DB445",
      "publisher": "GOOGLE LLC",
      "registryChangeCount": "30",
      "relatedToThreat": "False",
      "rpid": null,
      "signatureSignedInvalidReason": null,
      "signedStatus": "signed",
      "siteId": "1015875214652745972",
      "siteName": "WinWStest",
      "srcProcActiveContentFileId": null,
      "srcProcActiveContentHash": null,
      "srcProcActiveContentPath": null,
      "srcProcActiveContentSignedStatus": "unsigned",
      "srcProcActiveContentType": "FILE",
      "srcProcBinaryisExecutable": "True",
      "srcProcCmdLine": "\"C:\\Program Files (x86)\\Google\\Chrome\\Application\\chrome.exe\" --origin-trial-disabled-features=CaptureHandle --restore-last-session --flag-switches-begin --flag-switches-end",
      "srcProcDisplayName": "Google Chrome",
      "srcProcImageMd5": "1f8a0a7ed17e8f628598939dcaaa354e",
      "srcProcImagePath": "C:\\Program Files (x86)\\Google\\Chrome\\Application\\chrome.exe",
      "srcProcImageSha1": "84bc7424b07d5c3589317e5311e5ffaa60a38b62",
      "srcProcImageSha256": "196fc80802c7a409e92736de0f4c056d4d504df3ce4b0ac17ac3176b535171ed",
      "srcProcIntegrityLevel": "MEDIUM",
      "srcProcIsNative64Bit": "False",
      "srcProcIsRedirectCmdProcessor": "False",
      "srcProcIsStorylineRoot": "False",
      "srcProcName": "chrome.exe",
      "srcProcParentImageMd5": "a98d71eb1bec5d38549b2155a3e54008",
      "srcProcParentImagePath": "C:\\Program Files (x86)\\Google\\Chrome\\Temp\\scoped_dir21036_1816210371\\old_chrome.exe",
      "srcProcParentImageSha1": "8bfc5af325534d4b4b690c4883e27e3d005eee20",
      "srcProcParentImageSha256": "e6d9df99f3bce911f8241e4e40784288b879b93feaeb5edddb1cb4e0cac675f8",
      "srcProcParentName": "old_chrome.exe",
      "srcProcParentPid": "18184",
      "srcProcParentProcUid": "61D32E0AAB0D437F",
      "srcProcParentStartTime": "2021-12-12T13:49:34.015Z",
      "srcProcParentUid": "61D32E0AAB0D437F",
      "srcProcPid": "20888",
      "srcProcPublisher": "GOOGLE LLC",
      "srcProcReasonSignatureInvalid": null,
      "srcProcRelatedToThreat": "False",
      "srcProcRpid": null,
      "srcProcSessionId": "1",
      "srcProcSignedStatus": "signed",
      "srcProcStartTime": "2021-12-12T13:49:41.897Z",
      "srcProcStorylineId": "23A168D9150068D0",
      "srcProcSubsystem": "SYS_WIN32",
      "srcProcTid": null,
      "srcProcUid": "F9317943001DB445",
      "srcProcUser": "AD\\Joshua.Vigil",
      "srcProcVerifiedStatus": "verified",
      "storyline": "23A168D9150068D0",
      "tgtFileCreationCount": "85",
      "tgtFileDeletionCount": "1217",
      "tgtFileModificationCount": "165",
      "tiOriginalEventId": null,
      "tiOriginalEventIndex": null,
      "tiOriginalEventTraceId": null,
      "tid": null,
      "tiindicatorRelatedEventTime": null,
      "traceId": "01FPQEJCE3VASR5V7ATF25AQQN",
      "trueContext": "23A168D9150068D0",
      "url": "https://hq-logger01.gdit.com/logger/search.ftl?ehr=1&ausm_query=%2245.137.155.55/ex.sh%22%20OR%20%2245.137.155.55/kinsing%22%20OR%20%2280.71.158.12/libsystem.so%22%20OR%20%2280.71.158.12/kinsing%22%20OR%20%2280.71.158.12/Exploit69ogQNSQYz.class%22&from=$CurrentMonth&to=$Now&search_time=received_time",
      "urlAction": null,
      "user": "AD\\Joshua.Vigil",
      "verifiedStatus": "verified"
    },
    {
      "activeContentFileId": null,
      "activeContentHash": null,
      "activeContentPath": null,
      "activeContentSignedStatus": "unsigned",
      "activeContentType": "FILE",
      "agentDomain": "AD",
      "agentGroupId": "1022424678582482088",
      "agentId": "1036163683371316806",
      "agentInfected": false,
      "agentIp": "172.31.18.165",
      "agentIsActive": true,
      "agentIsDecommissioned": false,
      "agentMachineType": "laptop",
      "agentName": "F5310-285NXT2-L",
      "agentNetworkStatus": "connected",
      "agentOs": "windows",
      "agentTimestamp": "2021-12-12T13:49:55.654Z",
      "agentUuid": "f679d7b3265a46fc8cbc73f39cbf1107",
      "agentVersion": "21.6.4.423",
      "childProcCount": "12",
      "createdAt": "2021-12-12T13:49:55.654000Z",
      "crossProcCount": "237",
      "crossProcDupRemoteProcHandleCount": "229",
      "crossProcDupThreadHandleCount": "8",
      "crossProcOpenProcCount": "0",
      "crossProcOutOfStorylineCount": "0",
      "crossProcThreadCreateCount": "0",
      "dnsCount": "0",
      "endpointMachineType": "laptop",
      "endpointName": "F5310-285NXT2-L",
      "endpointOs": "windows",
      "eventIndex": "764",
      "eventTime": "2021-12-12T13:49:55.654Z",
      "eventType": "Not Reported",
      "fileIsExecutable": "True",
      "fileMd5": "1f8a0a7ed17e8f628598939dcaaa354e",
      "fileSha256": "196fc80802c7a409e92736de0f4c056d4d504df3ce4b0ac17ac3176b535171ed",
      "id": "631543045058199552",
      "indicatorBootConfigurationUpdateCount": "0",
      "indicatorEvasionCount": "8",
      "indicatorExploitationCount": "1",
      "indicatorGeneralCount": "0",
      "indicatorInfostealerCount": "0",
      "indicatorInjectionCount": "0",
      "indicatorPersistenceCount": "0",
      "indicatorPostExploitationCount": "0",
      "indicatorRansomwareCount": "0",
      "indicatorReconnaissanceCount": "0",
      "metaEventName": "HTTP",
      "moduleCount": "241",
      "netConnCount": "0",
      "netConnInCount": "0",
      "netConnOutCount": "0",
      "networkMethod": null,
      "networkSource": "CHROME",
      "networkUrl": "https://hq-logger01.gdit.com/logger/search.ftl?ehr=1&ausm_query=%2245.137.155.55/ex.sh%22%20OR%20%2245.137.155.55/kinsing%22%20OR%20%2280.71.158.12/libsystem.so%22%20OR%20%2280.71.158.12/kinsing%22%20OR%20%2280.71.158.12/Exploit69ogQNSQYz.class%22&from=$CurrentMonth&to=$Now&search_time=received_time",
      "objectType": "url",
      "parentPid": "18184",
      "parentProcessName": "old_chrome.exe",
      "parentProcessStartTime": "2021-12-12T13:49:34.015Z",
      "parentProcessUniqueKey": "F9317943001DB445",
      "pid": "20888",
      "processCmd": "\"C:\\Program Files (x86)\\Google\\Chrome\\Application\\chrome.exe\" --origin-trial-disabled-features=CaptureHandle --restore-last-session --flag-switches-begin --flag-switches-end",
      "processDisplayName": "Google Chrome",
      "processGroupId": "23A168D9150068D0",
      "processImagePath": "C:\\Program Files (x86)\\Google\\Chrome\\Application\\chrome.exe",
      "processImageSha1Hash": "84bc7424b07d5c3589317e5311e5ffaa60a38b62",
      "processIntegrityLevel": "MEDIUM",
      "processIsRedirectedCommandProcessor": "False",
      "processIsWow64": "False",
      "processName": "chrome.exe",
      "processRoot": "False",
      "processSessionId": "1",
      "processStartTime": "2021-12-12T13:49:41.897Z",
      "processSubSystem": "SYS_WIN32",
      "processUniqueKey": "F9317943001DB445",
      "publisher": "GOOGLE LLC",
      "registryChangeCount": "20",
      "relatedToThreat": "False",
      "rpid": null,
      "signatureSignedInvalidReason": null,
      "signedStatus": "signed",
      "siteId": "1015875214652745972",
      "siteName": "WinWStest",
      "srcProcActiveContentFileId": null,
      "srcProcActiveContentHash": null,
      "srcProcActiveContentPath": null,
      "srcProcActiveContentSignedStatus": "unsigned",
      "srcProcActiveContentType": "FILE",
      "srcProcBinaryisExecutable": "True",
      "srcProcCmdLine": "\"C:\\Program Files (x86)\\Google\\Chrome\\Application\\chrome.exe\" --origin-trial-disabled-features=CaptureHandle --restore-last-session --flag-switches-begin --flag-switches-end",
      "srcProcDisplayName": "Google Chrome",
      "srcProcImageMd5": "1f8a0a7ed17e8f628598939dcaaa354e",
      "srcProcImagePath": "C:\\Program Files (x86)\\Google\\Chrome\\Application\\chrome.exe",
      "srcProcImageSha1": "84bc7424b07d5c3589317e5311e5ffaa60a38b62",
      "srcProcImageSha256": "196fc80802c7a409e92736de0f4c056d4d504df3ce4b0ac17ac3176b535171ed",
      "srcProcIntegrityLevel": "MEDIUM",
      "srcProcIsNative64Bit": "False",
      "srcProcIsRedirectCmdProcessor": "False",
      "srcProcIsStorylineRoot": "False",
      "srcProcName": "chrome.exe",
      "srcProcParentImageMd5": "a98d71eb1bec5d38549b2155a3e54008",
      "srcProcParentImagePath": "C:\\Program Files (x86)\\Google\\Chrome\\Temp\\scoped_dir21036_1816210371\\old_chrome.exe",
      "srcProcParentImageSha1": "8bfc5af325534d4b4b690c4883e27e3d005eee20",
      "srcProcParentImageSha256": "e6d9df99f3bce911f8241e4e40784288b879b93feaeb5edddb1cb4e0cac675f8",
      "srcProcParentName": "old_chrome.exe",
      "srcProcParentPid": "18184",
      "srcProcParentProcUid": "61D32E0AAB0D437F",
      "srcProcParentStartTime": "2021-12-12T13:49:34.015Z",
      "srcProcParentUid": "61D32E0AAB0D437F",
      "srcProcPid": "20888",
      "srcProcPublisher": "GOOGLE LLC",
      "srcProcReasonSignatureInvalid": null,
      "srcProcRelatedToThreat": "False",
      "srcProcRpid": null,
      "srcProcSessionId": "1",
      "srcProcSignedStatus": "signed",
      "srcProcStartTime": "2021-12-12T13:49:41.897Z",
      "srcProcStorylineId": "23A168D9150068D0",
      "srcProcSubsystem": "SYS_WIN32",
      "srcProcTid": null,
      "srcProcUid": "F9317943001DB445",
      "srcProcUser": "AD\\Joshua.Vigil",
      "srcProcVerifiedStatus": "verified",
      "storyline": "23A168D9150068D0",
      "tgtFileCreationCount": "62",
      "tgtFileDeletionCount": "532",
      "tgtFileModificationCount": "127",
      "tiOriginalEventId": null,
      "tiOriginalEventIndex": null,
      "tiOriginalEventTraceId": null,
      "tid": null,
      "tiindicatorRelatedEventTime": null,
      "traceId": "01FPQEJBH5B52YZP9SJVZWNB19",
      "trueContext": "23A168D9150068D0",
      "url": "https://hq-logger01.gdit.com/logger/search.ftl?ehr=1&ausm_query=%2245.137.155.55/ex.sh%22%20OR%20%2245.137.155.55/kinsing%22%20OR%20%2280.71.158.12/libsystem.so%22%20OR%20%2280.71.158.12/kinsing%22%20OR%20%2280.71.158.12/Exploit69ogQNSQYz.class%22&from=$CurrentMonth&to=$Now&search_time=received_time",
      "urlAction": null,
      "user": "AD\\Joshua.Vigil",
      "verifiedStatus": "verified"
    },
    {
      "activeContentFileId": null,
      "activeContentHash": null,
      "activeContentPath": null,
      "activeContentSignedStatus": null,
      "activeContentType": null,
      "agentDomain": "AD",
      "agentGroupId": "1018129828852811657",
      "agentId": "1185500290778250077",
      "agentInfected": false,
      "agentIp": "172.31.18.165",
      "agentIsActive": true,
      "agentIsDecommissioned": false,
      "agentMachineType": "laptop",
      "agentName": "F4350-FMXY2D3-L",
      "agentNetworkStatus": "connected",
      "agentOs": "windows",
      "agentTimestamp": "2021-12-11T12:07:53.260Z",
      "agentUuid": "13e305e86c1f4ab0a5e3e16858587c43",
      "agentVersion": "21.6.4.423",
      "childProcCount": "1",
      "connectionStatus": "SUCCESS",
      "containerId": null,
      "containerImage": null,
      "containerLabels": null,
      "containerName": null,
      "createdAt": "2021-12-11T12:07:53.260000Z",
      "crossProcCount": "8951",
      "crossProcDupRemoteProcHandleCount": "0",
      "crossProcDupThreadHandleCount": "0",
      "crossProcOpenProcCount": "8951",
      "crossProcOutOfStorylineCount": "8951",
      "crossProcThreadCreateCount": "0",
      "direction": "OUTGOING",
      "dnsCount": "286",
      "dstIp": "62.210.130.250",
      "dstPort": 80,
      "endpointMachineType": "laptop",
      "endpointName": "F4350-FMXY2D3-L",
      "endpointOs": "windows",
      "eventIndex": "297",
      "eventTime": "2021-12-11T12:07:53.260Z",
      "eventType": "IP Connect",
      "fileIsExecutable": "True",
      "fileMd5": "b556ed3aedb71a026a3f592fdf5c2bf2",
      "fileSha256": "3143e2e377d4f06a3e13e332f99a2627ccda6d20bfc3bd5a6403e9430afe8f3d",
      "id": "631543045116919811",
      "indicatorBootConfigurationUpdateCount": "0",
      "indicatorEvasionCount": "1",
      "indicatorExploitationCount": "0",
      "indicatorGeneralCount": "0",
      "indicatorInfostealerCount": "0",
      "indicatorInjectionCount": "0",
      "indicatorPersistenceCount": "0",
      "indicatorPostExploitationCount": "0",
      "indicatorRansomwareCount": "0",
      "indicatorReconnaissanceCount": "0",
      "k8sClusterName": null,
      "k8sControllerLabels": null,
      "k8sControllerName": null,
      "k8sControllerType": null,
      "k8sNamespace": null,
      "k8sNamespaceLabels": null,
      "k8sNode": null,
      "k8sPodLabels": null,
      "k8sPodName": null,
      "metaEventName": "TCPV4",
      "moduleCount": "72",
      "netConnCount": "19204",
      "netConnInCount": "9488",
      "netConnOutCount": "9716",
      "netConnStatus": "SUCCESS",
      "netEventDirection": "OUTGOING",
      "netProtocolName": "http",
      "objectType": "ip",
      "parentPid": "4052",
      "parentProcessName": "DgAgent.exe",
      "parentProcessStartTime": "2021-12-09T16:37:09.182Z",
      "parentProcessUniqueKey": "03EA8FE666185FE7",
      "pid": "11344",
      "processCmd": "\"C:\\Program Files\\DGAgent\\dgwip.exe\" -basedir \"C:\\Program Files\\DGAgent\\dgwip\\V47.cfg\\\\\"",
      "processDisplayName": "dgwip 7.6.2.0058",
      "processGroupId": "909689807ADEE2B0",
      "processImagePath": "C:\\Program Files\\DGAgent\\DgWip.exe",
      "processImageSha1Hash": "8799aa5a32ece1c5b6f7ff17065128b4a9a44d59",
      "processIntegrityLevel": "SYSTEM",
      "processIsRedirectedCommandProcessor": "False",
      "processIsWow64": "False",
      "processName": "DgWip.exe",
      "processRoot": "False",
      "processSessionId": "0",
      "processStartTime": "2021-12-09T16:37:14.794Z",
      "processSubSystem": "SYS_WIN32",
      "processUniqueKey": "03EA8FE666185FE7",
      "publisher": "DIGITAL GUARDIAN, INC.",
      "registryChangeCount": "8",
      "relatedToThreat": "False",
      "rpid": null,
      "signatureSignedInvalidReason": null,
      "signedStatus": "signed",
      "siteId": "1018128563204802241",
      "siteName": "WinWS",
      "srcIp": "10.0.0.99",
      "srcPort": 54647,
      "srcProcActiveContentFileId": null,
      "srcProcActiveContentHash": null,
      "srcProcActiveContentPath": null,
      "srcProcActiveContentSignedStatus": null,
      "srcProcActiveContentType": null,
      "srcProcBinaryisExecutable": "True",
      "srcProcCmdLine": "\"C:\\Program Files\\DGAgent\\dgwip.exe\" -basedir \"C:\\Program Files\\DGAgent\\dgwip\\V47.cfg\\\\\"",
      "srcProcDisplayName": "dgwip 7.6.2.0058",
      "srcProcImageMd5": "b556ed3aedb71a026a3f592fdf5c2bf2",
      "srcProcImagePath": "C:\\Program Files\\DGAgent\\DgWip.exe",
      "srcProcImageSha1": "8799aa5a32ece1c5b6f7ff17065128b4a9a44d59",
      "srcProcImageSha256": "3143e2e377d4f06a3e13e332f99a2627ccda6d20bfc3bd5a6403e9430afe8f3d",
      "srcProcIntegrityLevel": "SYSTEM",
      "srcProcIsNative64Bit": "False",
      "srcProcIsRedirectCmdProcessor": "False",
      "srcProcIsStorylineRoot": "False",
      "srcProcName": "DgWip.exe",
      "srcProcParentImageMd5": "f3c4890bb55a4b72c23cc4b2a91af8eb",
      "srcProcParentImagePath": "C:\\Program Files\\DGAgent\\DgAgent.exe",
      "srcProcParentImageSha1": "2c80b177c9c37c45ad7c67ce292b131ac4af9a2e",
      "srcProcParentImageSha256": "c773c73434e370a819483f28db3540fec95e949208d666b45324e5bb41e856f0",
      "srcProcParentName": "DgAgent.exe",
      "srcProcParentPid": "4052",
      "srcProcParentProcUid": "CEB631714232A762",
      "srcProcParentStartTime": "2021-12-09T16:37:09.182Z",
      "srcProcParentUid": "CEB631714232A762",
      "srcProcPid": "11344",
      "srcProcPublisher": "DIGITAL GUARDIAN, INC.",
      "srcProcReasonSignatureInvalid": null,
      "srcProcRelatedToThreat": "False",
      "srcProcRpid": null,
      "srcProcSessionId": "0",
      "srcProcSignedStatus": "signed",
      "srcProcStartTime": "2021-12-09T16:37:14.794Z",
      "srcProcStorylineId": "909689807ADEE2B0",
      "srcProcSubsystem": "SYS_WIN32",
      "srcProcTid": null,
      "srcProcUid": "03EA8FE666185FE7",
      "srcProcUser": "NT AUTHORITY\\SYSTEM",
      "srcProcVerifiedStatus": "verified",
      "storyline": "909689807ADEE2B0",
      "tgtFileCreationCount": "0",
      "tgtFileDeletionCount": "0",
      "tgtFileModificationCount": "3",
      "tiOriginalEventId": null,
      "tiOriginalEventIndex": null,
      "tiOriginalEventTraceId": null,
      "tid": null,
      "tiindicatorRelatedEventTime": null,
      "traceId": "01FPMPBZH9XZ673WPHR5D45WZ3",
      "trueContext": "909689807ADEE2B0",
      "user": "NT AUTHORITY\\SYSTEM",
      "verifiedStatus": "verified"
    },
    {
      "activeContentFileId": null,
      "activeContentHash": null,
      "activeContentPath": null,
      "activeContentSignedStatus": null,
      "activeContentType": null,
      "agentDomain": "AD",
      "agentGroupId": "1018129828852811657",
      "agentId": "1185500290778250077",
      "agentInfected": false,
      "agentIp": "172.31.18.165",
      "agentIsActive": true,
      "agentIsDecommissioned": false,
      "agentMachineType": "laptop",
      "agentName": "F4350-FMXY2D3-L",
      "agentNetworkStatus": "connected",
      "agentOs": "windows",
      "agentTimestamp": "2021-12-11T12:07:52.807Z",
      "agentUuid": "13e305e86c1f4ab0a5e3e16858587c43",
      "agentVersion": "21.6.4.423",
      "childProcCount": "1",
      "connectionStatus": "SUCCESS",
      "containerId": null,
      "containerImage": null,
      "containerLabels": null,
      "containerName": null,
      "createdAt": "2021-12-11T12:07:52.807000Z",
      "crossProcCount": "8951",
      "crossProcDupRemoteProcHandleCount": "0",
      "crossProcDupThreadHandleCount": "0",
      "crossProcOpenProcCount": "8951",
      "crossProcOutOfStorylineCount": "8951",
      "crossProcThreadCreateCount": "0",
      "direction": "OUTGOING",
      "dnsCount": "286",
      "dstIp": "62.210.130.250",
      "dstPort": 80,
      "endpointMachineType": "laptop",
      "endpointName": "F4350-FMXY2D3-L",
      "endpointOs": "windows",
      "eventIndex": "281",
      "eventTime": "2021-12-11T12:07:52.807Z",
      "eventType": "IP Connect",
      "fileIsExecutable": "True",
      "fileMd5": "b556ed3aedb71a026a3f592fdf5c2bf2",
      "fileSha256": "3143e2e377d4f06a3e13e332f99a2627ccda6d20bfc3bd5a6403e9430afe8f3d",
      "id": "631543045116919810",
      "indicatorBootConfigurationUpdateCount": "0",
      "indicatorEvasionCount": "1",
      "indicatorExploitationCount": "0",
      "indicatorGeneralCount": "0",
      "indicatorInfostealerCount": "0",
      "indicatorInjectionCount": "0",
      "indicatorPersistenceCount": "0",
      "indicatorPostExploitationCount": "0",
      "indicatorRansomwareCount": "0",
      "indicatorReconnaissanceCount": "0",
      "k8sClusterName": null,
      "k8sControllerLabels": null,
      "k8sControllerName": null,
      "k8sControllerType": null,
      "k8sNamespace": null,
      "k8sNamespaceLabels": null,
      "k8sNode": null,
      "k8sPodLabels": null,
      "k8sPodName": null,
      "metaEventName": "TCPV4",
      "moduleCount": "72",
      "netConnCount": "19204",
      "netConnInCount": "9488",
      "netConnOutCount": "9716",
      "netConnStatus": "SUCCESS",
      "netEventDirection": "OUTGOING",
      "netProtocolName": "http",
      "objectType": "ip",
      "parentPid": "4052",
      "parentProcessName": "DgAgent.exe",
      "parentProcessStartTime": "2021-12-09T16:37:09.182Z",
      "parentProcessUniqueKey": "03EA8FE666185FE7",
      "pid": "11344",
      "processCmd": "\"C:\\Program Files\\DGAgent\\dgwip.exe\" -basedir \"C:\\Program Files\\DGAgent\\dgwip\\V47.cfg\\\\\"",
      "processDisplayName": "dgwip 7.6.2.0058",
      "processGroupId": "909689807ADEE2B0",
      "processImagePath": "C:\\Program Files\\DGAgent\\DgWip.exe",
      "processImageSha1Hash": "8799aa5a32ece1c5b6f7ff17065128b4a9a44d59",
      "processIntegrityLevel": "SYSTEM",
      "processIsRedirectedCommandProcessor": "False",
      "processIsWow64": "False",
      "processName": "DgWip.exe",
      "processRoot": "False",
      "processSessionId": "0",
      "processStartTime": "2021-12-09T16:37:14.794Z",
      "processSubSystem": "SYS_WIN32",
      "processUniqueKey": "03EA8FE666185FE7",
      "publisher": "DIGITAL GUARDIAN, INC.",
      "registryChangeCount": "8",
      "relatedToThreat": "False",
      "rpid": null,
      "signatureSignedInvalidReason": null,
      "signedStatus": "signed",
      "siteId": "1018128563204802241",
      "siteName": "WinWS",
      "srcIp": "10.0.0.99",
      "srcPort": 54645,
      "srcProcActiveContentFileId": null,
      "srcProcActiveContentHash": null,
      "srcProcActiveContentPath": null,
      "srcProcActiveContentSignedStatus": null,
      "srcProcActiveContentType": null,
      "srcProcBinaryisExecutable": "True",
      "srcProcCmdLine": "\"C:\\Program Files\\DGAgent\\dgwip.exe\" -basedir \"C:\\Program Files\\DGAgent\\dgwip\\V47.cfg\\\\\"",
      "srcProcDisplayName": "dgwip 7.6.2.0058",
      "srcProcImageMd5": "b556ed3aedb71a026a3f592fdf5c2bf2",
      "srcProcImagePath": "C:\\Program Files\\DGAgent\\DgWip.exe",
      "srcProcImageSha1": "8799aa5a32ece1c5b6f7ff17065128b4a9a44d59",
      "srcProcImageSha256": "3143e2e377d4f06a3e13e332f99a2627ccda6d20bfc3bd5a6403e9430afe8f3d",
      "srcProcIntegrityLevel": "SYSTEM",
      "srcProcIsNative64Bit": "False",
      "srcProcIsRedirectCmdProcessor": "False",
      "srcProcIsStorylineRoot": "False",
      "srcProcName": "DgWip.exe",
      "srcProcParentImageMd5": "f3c4890bb55a4b72c23cc4b2a91af8eb",
      "srcProcParentImagePath": "C:\\Program Files\\DGAgent\\DgAgent.exe",
      "srcProcParentImageSha1": "2c80b177c9c37c45ad7c67ce292b131ac4af9a2e",
      "srcProcParentImageSha256": "c773c73434e370a819483f28db3540fec95e949208d666b45324e5bb41e856f0",
      "srcProcParentName": "DgAgent.exe",
      "srcProcParentPid": "4052",
      "srcProcParentProcUid": "CEB631714232A762",
      "srcProcParentStartTime": "2021-12-09T16:37:09.182Z",
      "srcProcParentUid": "CEB631714232A762",
      "srcProcPid": "11344",
      "srcProcPublisher": "DIGITAL GUARDIAN, INC.",
      "srcProcReasonSignatureInvalid": null,
      "srcProcRelatedToThreat": "False",
      "srcProcRpid": null,
      "srcProcSessionId": "0",
      "srcProcSignedStatus": "signed",
      "srcProcStartTime": "2021-12-09T16:37:14.794Z",
      "srcProcStorylineId": "909689807ADEE2B0",
      "srcProcSubsystem": "SYS_WIN32",
      "srcProcTid": null,
      "srcProcUid": "03EA8FE666185FE7",
      "srcProcUser": "NT AUTHORITY\\SYSTEM",
      "srcProcVerifiedStatus": "verified",
      "storyline": "909689807ADEE2B0",
      "tgtFileCreationCount": "0",
      "tgtFileDeletionCount": "0",
      "tgtFileModificationCount": "3",
      "tiOriginalEventId": null,
      "tiOriginalEventIndex": null,
      "tiOriginalEventTraceId": null,
      "tid": null,
      "tiindicatorRelatedEventTime": null,
      "traceId": "01FPMPBZH9XZ673WPHR5D45WZ3",
      "trueContext": "909689807ADEE2B0",
      "user": "NT AUTHORITY\\SYSTEM",
      "verifiedStatus": "verified"
    },
    {
      "activeContentFileId": null,
      "activeContentHash": null,
      "activeContentPath": null,
      "activeContentSignedStatus": "unsigned",
      "activeContentType": "FILE",
      "agentDomain": "AD",
      "agentGroupId": "1018129828852811657",
      "agentId": "1104551050201890355",
      "agentInfected": false,
      "agentIp": "172.31.18.165",
      "agentIsActive": true,
      "agentIsDecommissioned": false,
      "agentMachineType": "laptop",
      "agentName": "F5310-49LPXT2-L",
      "agentNetworkStatus": "connected",
      "agentOs": "windows",
      "agentTimestamp": "2021-12-11T05:05:16.550Z",
      "agentUuid": "6730bd0bd47a4a22a4a1696059ba2050",
      "agentVersion": "21.6.4.423",
      "childProcCount": "1301",
      "createdAt": "2021-12-11T05:05:16.550000Z",
      "crossProcCount": "272770",
      "crossProcDupRemoteProcHandleCount": "269337",
      "crossProcDupThreadHandleCount": "3433",
      "crossProcOpenProcCount": "0",
      "crossProcOutOfStorylineCount": "0",
      "crossProcThreadCreateCount": "0",
      "dnsCount": "0",
      "endpointMachineType": "laptop",
      "endpointName": "F5310-49LPXT2-L",
      "endpointOs": "windows",
      "eventIndex": "395",
      "eventTime": "2021-12-11T05:05:16.550Z",
      "eventType": "Not Reported",
      "fileIsExecutable": "True",
      "fileMd5": "1f8a0a7ed17e8f628598939dcaaa354e",
      "fileSha256": "196fc80802c7a409e92736de0f4c056d4d504df3ce4b0ac17ac3176b535171ed",
      "id": "631543045116919813",
      "indicatorBootConfigurationUpdateCount": "0",
      "indicatorEvasionCount": "1273",
      "indicatorExploitationCount": "153",
      "indicatorGeneralCount": "12",
      "indicatorInfostealerCount": "0",
      "indicatorInjectionCount": "0",
      "indicatorPersistenceCount": "0",
      "indicatorPostExploitationCount": "0",
      "indicatorRansomwareCount": "0",
      "indicatorReconnaissanceCount": "0",
      "metaEventName": "HTTP",
      "moduleCount": "4492",
      "netConnCount": "1",
      "netConnInCount": "0",
      "netConnOutCount": "1",
      "networkMethod": null,
      "networkSource": "CHROME",
      "networkUrl": "http://www.dnslog.cn/",
      "objectType": "url",
      "parentPid": "34488",
      "parentProcessName": "explorer.exe",
      "parentProcessStartTime": "2021-12-07T13:54:39.624Z",
      "parentProcessUniqueKey": "3BB87E49FFB3FA08",
      "pid": "32264",
      "processCmd": "\"C:\\Program Files (x86)\\Google\\Chrome\\Application\\chrome.exe\"",
      "processDisplayName": "Google Chrome",
      "processGroupId": "6D902B7A48DF4C22",
      "processImagePath": "C:\\Program Files (x86)\\Google\\Chrome\\Application\\chrome.exe",
      "processImageSha1Hash": "84bc7424b07d5c3589317e5311e5ffaa60a38b62",
      "processIntegrityLevel": "MEDIUM",
      "processIsRedirectedCommandProcessor": "False",
      "processIsWow64": "False",
      "processName": "chrome.exe",
      "processRoot": "True",
      "processSessionId": "4",
      "processStartTime": "2021-12-08T13:45:34.433Z",
      "processSubSystem": "SYS_WIN32",
      "processUniqueKey": "3BB87E49FFB3FA08",
      "publisher": "GOOGLE LLC",
      "registryChangeCount": "2477",
      "relatedToThreat": "False",
      "rpid": null,
      "signatureSignedInvalidReason": null,
      "signedStatus": "signed",
      "siteId": "1018128563204802241",
      "siteName": "WinWS",
      "srcProcActiveContentFileId": null,
      "srcProcActiveContentHash": null,
      "srcProcActiveContentPath": null,
      "srcProcActiveContentSignedStatus": "unsigned",
      "srcProcActiveContentType": "FILE",
      "srcProcBinaryisExecutable": "True",
      "srcProcCmdLine": "\"C:\\Program Files (x86)\\Google\\Chrome\\Application\\chrome.exe\"",
      "srcProcDisplayName": "Google Chrome",
      "srcProcImageMd5": "1f8a0a7ed17e8f628598939dcaaa354e",
      "srcProcImagePath": "C:\\Program Files (x86)\\Google\\Chrome\\Application\\chrome.exe",
      "srcProcImageSha1": "84bc7424b07d5c3589317e5311e5ffaa60a38b62",
      "srcProcImageSha256": "196fc80802c7a409e92736de0f4c056d4d504df3ce4b0ac17ac3176b535171ed",
      "srcProcIntegrityLevel": "MEDIUM",
      "srcProcIsNative64Bit": "False",
      "srcProcIsRedirectCmdProcessor": "False",
      "srcProcIsStorylineRoot": "True",
      "srcProcName": "chrome.exe",
      "srcProcParentImageMd5": "681a21a3b848ed960073475cd77634ce",
      "srcProcParentImagePath": "C:\\WINDOWS\\explorer.exe",
      "srcProcParentImageSha1": "3d930943fbea03c9330c4947e5749ed9ceed528a",
      "srcProcParentImageSha256": "08d3f16dfbb5b5d7b419376a4f73350c13424de984fd43309160ce30bc1df089",
      "srcProcParentName": "explorer.exe",
      "srcProcParentPid": "34488",
      "srcProcParentProcUid": "48DB25F84F0FC7BE",
      "srcProcParentStartTime": "2021-12-07T13:54:39.624Z",
      "srcProcParentUid": "48DB25F84F0FC7BE",
      "srcProcPid": "32264",
      "srcProcPublisher": "GOOGLE LLC",
      "srcProcReasonSignatureInvalid": null,
      "srcProcRelatedToThreat": "False",
      "srcProcRpid": null,
      "srcProcSessionId": "4",
      "srcProcSignedStatus": "signed",
      "srcProcStartTime": "2021-12-08T13:45:34.433Z",
      "srcProcStorylineId": "6D902B7A48DF4C22",
      "srcProcSubsystem": "SYS_WIN32",
      "srcProcTid": null,
      "srcProcUid": "3BB87E49FFB3FA08",
      "srcProcUser": "AD\\Frank.Olmstead",
      "srcProcVerifiedStatus": "verified",
      "storyline": "6D902B7A48DF4C22",
      "tgtFileCreationCount": "22817",
      "tgtFileDeletionCount": "20181",
      "tgtFileModificationCount": "57204",
      "tiOriginalEventId": null,
      "tiOriginalEventIndex": null,
      "tiOriginalEventTraceId": null,
      "tid": null,
      "tiindicatorRelatedEventTime": null,
      "traceId": "01FPKY5AR2ASP006923KDX3K7B",
      "trueContext": "6D902B7A48DF4C22",
      "url": "http://www.dnslog.cn/",
      "urlAction": null,
      "user": "AD\\Frank.Olmstead",
      "verifiedStatus": "verified"
    },
    {
      "activeContentFileId": null,
      "activeContentHash": null,
      "activeContentPath": null,
      "activeContentSignedStatus": "unsigned",
      "activeContentType": "FILE",
      "agentDomain": "AD",
      "agentGroupId": "1018129828852811657",
      "agentId": "1104551050201890355",
      "agentInfected": false,
      "agentIp": "172.31.18.165",
      "agentIsActive": true,
      "agentIsDecommissioned": false,
      "agentMachineType": "laptop",
      "agentName": "F5310-49LPXT2-L",
      "agentNetworkStatus": "connected",
      "agentOs": "windows",
      "agentTimestamp": "2021-12-11T05:04:06.514Z",
      "agentUuid": "6730bd0bd47a4a22a4a1696059ba2050",
      "agentVersion": "21.6.4.423",
      "childProcCount": "1300",
      "createdAt": "2021-12-11T05:04:06.514000Z",
      "crossProcCount": "272568",
      "crossProcDupRemoteProcHandleCount": "269138",
      "crossProcDupThreadHandleCount": "3430",
      "crossProcOpenProcCount": "0",
      "crossProcOutOfStorylineCount": "0",
      "crossProcThreadCreateCount": "0",
      "dnsCount": "0",
      "endpointMachineType": "laptop",
      "endpointName": "F5310-49LPXT2-L",
      "endpointOs": "windows",
      "eventIndex": "929",
      "eventTime": "2021-12-11T05:04:06.514Z",
      "eventType": "Not Reported",
      "fileIsExecutable": "True",
      "fileMd5": "1f8a0a7ed17e8f628598939dcaaa354e",
      "fileSha256": "196fc80802c7a409e92736de0f4c056d4d504df3ce4b0ac17ac3176b535171ed",
      "id": "631543045116919808",
      "indicatorBootConfigurationUpdateCount": "0",
      "indicatorEvasionCount": "1272",
      "indicatorExploitationCount": "153",
      "indicatorGeneralCount": "12",
      "indicatorInfostealerCount": "0",
      "indicatorInjectionCount": "0",
      "indicatorPersistenceCount": "0",
      "indicatorPostExploitationCount": "0",
      "indicatorRansomwareCount": "0",
      "indicatorReconnaissanceCount": "0",
      "metaEventName": "HTTP",
      "moduleCount": "4490",
      "netConnCount": "1",
      "netConnInCount": "0",
      "netConnOutCount": "1",
      "networkMethod": null,
      "networkSource": "CHROME",
      "networkUrl": "http://www.dnslog.cn/",
      "objectType": "url",
      "parentPid": "34488",
      "parentProcessName": "explorer.exe",
      "parentProcessStartTime": "2021-12-07T13:54:39.624Z",
      "parentProcessUniqueKey": "3BB87E49FFB3FA08",
      "pid": "32264",
      "processCmd": "\"C:\\Program Files (x86)\\Google\\Chrome\\Application\\chrome.exe\"",
      "processDisplayName": "Google Chrome",
      "processGroupId": "6D902B7A48DF4C22",
      "processImagePath": "C:\\Program Files (x86)\\Google\\Chrome\\Application\\chrome.exe",
      "processImageSha1Hash": "84bc7424b07d5c3589317e5311e5ffaa60a38b62",
      "processIntegrityLevel": "MEDIUM",
      "processIsRedirectedCommandProcessor": "False",
      "processIsWow64": "False",
      "processName": "chrome.exe",
      "processRoot": "True",
      "processSessionId": "4",
      "processStartTime": "2021-12-08T13:45:34.433Z",
      "processSubSystem": "SYS_WIN32",
      "processUniqueKey": "3BB87E49FFB3FA08",
      "publisher": "GOOGLE LLC",
      "registryChangeCount": "2476",
      "relatedToThreat": "False",
      "rpid": null,
      "signatureSignedInvalidReason": null,
      "signedStatus": "signed",
      "siteId": "1018128563204802241",
      "siteName": "WinWS",
      "srcProcActiveContentFileId": null,
      "srcProcActiveContentHash": null,
      "srcProcActiveContentPath": null,
      "srcProcActiveContentSignedStatus": "unsigned",
      "srcProcActiveContentType": "FILE",
      "srcProcBinaryisExecutable": "True",
      "srcProcCmdLine": "\"C:\\Program Files (x86)\\Google\\Chrome\\Application\\chrome.exe\"",
      "srcProcDisplayName": "Google Chrome",
      "srcProcImageMd5": "1f8a0a7ed17e8f628598939dcaaa354e",
      "srcProcImagePath": "C:\\Program Files (x86)\\Google\\Chrome\\Application\\chrome.exe",
      "srcProcImageSha1": "84bc7424b07d5c3589317e5311e5ffaa60a38b62",
      "srcProcImageSha256": "196fc80802c7a409e92736de0f4c056d4d504df3ce4b0ac17ac3176b535171ed",
      "srcProcIntegrityLevel": "MEDIUM",
      "srcProcIsNative64Bit": "False",
      "srcProcIsRedirectCmdProcessor": "False",
      "srcProcIsStorylineRoot": "True",
      "srcProcName": "chrome.exe",
      "srcProcParentImageMd5": "681a21a3b848ed960073475cd77634ce",
      "srcProcParentImagePath": "C:\\WINDOWS\\explorer.exe",
      "srcProcParentImageSha1": "3d930943fbea03c9330c4947e5749ed9ceed528a",
      "srcProcParentImageSha256": "08d3f16dfbb5b5d7b419376a4f73350c13424de984fd43309160ce30bc1df089",
      "srcProcParentName": "explorer.exe",
      "srcProcParentPid": "34488",
      "srcProcParentProcUid": "48DB25F84F0FC7BE",
      "srcProcParentStartTime": "2021-12-07T13:54:39.624Z",
      "srcProcParentUid": "48DB25F84F0FC7BE",
      "srcProcPid": "32264",
      "srcProcPublisher": "GOOGLE LLC",
      "srcProcReasonSignatureInvalid": null,
      "srcProcRelatedToThreat": "False",
      "srcProcRpid": null,
      "srcProcSessionId": "4",
      "srcProcSignedStatus": "signed",
      "srcProcStartTime": "2021-12-08T13:45:34.433Z",
      "srcProcStorylineId": "6D902B7A48DF4C22",
      "srcProcSubsystem": "SYS_WIN32",
      "srcProcTid": null,
      "srcProcUid": "3BB87E49FFB3FA08",
      "srcProcUser": "AD\\Frank.Olmstead",
      "srcProcVerifiedStatus": "verified",
      "storyline": "6D902B7A48DF4C22",
      "tgtFileCreationCount": "22812",
      "tgtFileDeletionCount": "20177",
      "tgtFileModificationCount": "57195",
      "tiOriginalEventId": null,
      "tiOriginalEventIndex": null,
      "tiOriginalEventTraceId": null,
      "tid": null,
      "tiindicatorRelatedEventTime": null,
      "traceId": "01FPKY10YZQGZV8CGXAX1K03W5",
      "trueContext": "6D902B7A48DF4C22",
      "url": "http://www.dnslog.cn/",
      "urlAction": null,
      "user": "AD\\Frank.Olmstead",
      "verifiedStatus": "verified"
    },
    {
      "activeContentFileId": null,
      "activeContentHash": null,
      "activeContentPath": null,
      "activeContentSignedStatus": "unsigned",
      "activeContentType": "FILE",
      "agentDomain": "AD",
      "agentGroupId": "1018129828852811657",
      "agentId": "1104551050201890355",
      "agentInfected": false,
      "agentIp": "172.31.18.165",
      "agentIsActive": true,
      "agentIsDecommissioned": false,
      "agentMachineType": "laptop",
      "agentName": "F5310-49LPXT2-L",
      "agentNetworkStatus": "connected",
      "agentOs": "windows",
      "agentTimestamp": "2021-12-11T05:03:29.102Z",
      "agentUuid": "6730bd0bd47a4a22a4a1696059ba2050",
      "agentVersion": "21.6.4.423",
      "childProcCount": "1300",
      "createdAt": "2021-12-11T05:03:29.102000Z",
      "crossProcCount": "272568",
      "crossProcDupRemoteProcHandleCount": "269138",
      "crossProcDupThreadHandleCount": "3430",
      "crossProcOpenProcCount": "0",
      "crossProcOutOfStorylineCount": "0",
      "crossProcThreadCreateCount": "0",
      "dnsCount": "0",
      "endpointMachineType": "laptop",
      "endpointName": "F5310-49LPXT2-L",
      "endpointOs": "windows",
      "eventIndex": "1",
      "eventTime": "2021-12-11T05:03:29.102Z",
      "eventType": "Not Reported",
      "fileIsExecutable": "True",
      "fileMd5": "1f8a0a7ed17e8f628598939dcaaa354e",
      "fileSha256": "196fc80802c7a409e92736de0f4c056d4d504df3ce4b0ac17ac3176b535171ed",
      "id": "631543045104336896",
      "indicatorBootConfigurationUpdateCount": "0",
      "indicatorEvasionCount": "1272",
      "indicatorExploitationCount": "153",
      "indicatorGeneralCount": "12",
      "indicatorInfostealerCount": "0",
      "indicatorInjectionCount": "0",
      "indicatorPersistenceCount": "0",
      "indicatorPostExploitationCount": "0",
      "indicatorRansomwareCount": "0",
      "indicatorReconnaissanceCount": "0",
      "metaEventName": "HTTP",
      "moduleCount": "4490",
      "netConnCount": "1",
      "netConnInCount": "0",
      "netConnOutCount": "1",
      "networkMethod": null,
      "networkSource": "CHROME",
      "networkUrl": "http://www.dnslog.cn/",
      "objectType": "url",
      "parentPid": "34488",
      "parentProcessName": "explorer.exe",
      "parentProcessStartTime": "2021-12-07T13:54:39.624Z",
      "parentProcessUniqueKey": "3BB87E49FFB3FA08",
      "pid": "32264",
      "processCmd": "\"C:\\Program Files (x86)\\Google\\Chrome\\Application\\chrome.exe\"",
      "processDisplayName": "Google Chrome",
      "processGroupId": "6D902B7A48DF4C22",
      "processImagePath": "C:\\Program Files (x86)\\Google\\Chrome\\Application\\chrome.exe",
      "processImageSha1Hash": "84bc7424b07d5c3589317e5311e5ffaa60a38b62",
      "processIntegrityLevel": "MEDIUM",
      "processIsRedirectedCommandProcessor": "False",
      "processIsWow64": "False",
      "processName": "chrome.exe",
      "processRoot": "True",
      "processSessionId": "4",
      "processStartTime": "2021-12-08T13:45:34.433Z",
      "processSubSystem": "SYS_WIN32",
      "processUniqueKey": "3BB87E49FFB3FA08",
      "publisher": "GOOGLE LLC",
      "registryChangeCount": "2476",
      "relatedToThreat": "False",
      "rpid": null,
      "signatureSignedInvalidReason": null,
      "signedStatus": "signed",
      "siteId": "1018128563204802241",
      "siteName": "WinWS",
      "srcProcActiveContentFileId": null,
      "srcProcActiveContentHash": null,
      "srcProcActiveContentPath": null,
      "srcProcActiveContentSignedStatus": "unsigned",
      "srcProcActiveContentType": "FILE",
      "srcProcBinaryisExecutable": "True",
      "srcProcCmdLine": "\"C:\\Program Files (x86)\\Google\\Chrome\\Application\\chrome.exe\"",
      "srcProcDisplayName": "Google Chrome",
      "srcProcImageMd5": "1f8a0a7ed17e8f628598939dcaaa354e",
      "srcProcImagePath": "C:\\Program Files (x86)\\Google\\Chrome\\Application\\chrome.exe",
      "srcProcImageSha1": "84bc7424b07d5c3589317e5311e5ffaa60a38b62",
      "srcProcImageSha256": "196fc80802c7a409e92736de0f4c056d4d504df3ce4b0ac17ac3176b535171ed",
      "srcProcIntegrityLevel": "MEDIUM",
      "srcProcIsNative64Bit": "False",
      "srcProcIsRedirectCmdProcessor": "False",
      "srcProcIsStorylineRoot": "True",
      "srcProcName": "chrome.exe",
      "srcProcParentImageMd5": "681a21a3b848ed960073475cd77634ce",
      "srcProcParentImagePath": "C:\\WINDOWS\\explorer.exe",
      "srcProcParentImageSha1": "3d930943fbea03c9330c4947e5749ed9ceed528a",
      "srcProcParentImageSha256": "08d3f16dfbb5b5d7b419376a4f73350c13424de984fd43309160ce30bc1df089",
      "srcProcParentName": "explorer.exe",
      "srcProcParentPid": "34488",
      "srcProcParentProcUid": "48DB25F84F0FC7BE",
      "srcProcParentStartTime": "2021-12-07T13:54:39.624Z",
      "srcProcParentUid": "48DB25F84F0FC7BE",
      "srcProcPid": "32264",
      "srcProcPublisher": "GOOGLE LLC",
      "srcProcReasonSignatureInvalid": null,
      "srcProcRelatedToThreat": "False",
      "srcProcRpid": null,
      "srcProcSessionId": "4",
      "srcProcSignedStatus": "signed",
      "srcProcStartTime": "2021-12-08T13:45:34.433Z",
      "srcProcStorylineId": "6D902B7A48DF4C22",
      "srcProcSubsystem": "SYS_WIN32",
      "srcProcTid": null,
      "srcProcUid": "3BB87E49FFB3FA08",
      "srcProcUser": "AD\\Frank.Olmstead",
      "srcProcVerifiedStatus": "verified",
      "storyline": "6D902B7A48DF4C22",
      "tgtFileCreationCount": "22812",
      "tgtFileDeletionCount": "20177",
      "tgtFileModificationCount": "57195",
      "tiOriginalEventId": null,
      "tiOriginalEventIndex": null,
      "tiOriginalEventTraceId": null,
      "tid": null,
      "tiindicatorRelatedEventTime": null,
      "traceId": "01FPKY10YZQGZV8CGXAX1K03W5",
      "trueContext": "6D902B7A48DF4C22",
      "url": "http://www.dnslog.cn/",
      "urlAction": null,
      "user": "AD\\Frank.Olmstead",
      "verifiedStatus": "verified"
    },
    {
      "activeContentFileId": null,
      "activeContentHash": null,
      "activeContentPath": null,
      "activeContentSignedStatus": "unsigned",
      "activeContentType": "FILE",
      "agentDomain": "AD",
      "agentGroupId": "1018129828852811657",
      "agentId": "1104551050201890355",
      "agentInfected": false,
      "agentIp": "172.31.18.165",
      "agentIsActive": true,
      "agentIsDecommissioned": false,
      "agentMachineType": "laptop",
      "agentName": "F5310-49LPXT2-L",
      "agentNetworkStatus": "connected",
      "agentOs": "windows",
      "agentTimestamp": "2021-12-11T05:03:14.021Z",
      "agentUuid": "6730bd0bd47a4a22a4a1696059ba2050",
      "agentVersion": "21.6.4.423",
      "childProcCount": "1298",
      "createdAt": "2021-12-11T05:03:14.021000Z",
      "crossProcCount": "272408",
      "crossProcDupRemoteProcHandleCount": "268981",
      "crossProcDupThreadHandleCount": "3427",
      "crossProcOpenProcCount": "0",
      "crossProcOutOfStorylineCount": "0",
      "crossProcThreadCreateCount": "0",
      "dnsCount": "0",
      "endpointMachineType": "laptop",
      "endpointName": "F5310-49LPXT2-L",
      "endpointOs": "windows",
      "eventIndex": "822",
      "eventTime": "2021-12-11T05:03:14.021Z",
      "eventType": "Not Reported",
      "fileIsExecutable": "True",
      "fileMd5": "1f8a0a7ed17e8f628598939dcaaa354e",
      "fileSha256": "196fc80802c7a409e92736de0f4c056d4d504df3ce4b0ac17ac3176b535171ed",
      "id": "631543045116919809",
      "indicatorBootConfigurationUpdateCount": "0",
      "indicatorEvasionCount": "1270",
      "indicatorExploitationCount": "153",
      "indicatorGeneralCount": "12",
      "indicatorInfostealerCount": "0",
      "indicatorInjectionCount": "0",
      "indicatorPersistenceCount": "0",
      "indicatorPostExploitationCount": "0",
      "indicatorRansomwareCount": "0",
      "indicatorReconnaissanceCount": "0",
      "metaEventName": "HTTP",
      "moduleCount": "4490",
      "netConnCount": "1",
      "netConnInCount": "0",
      "netConnOutCount": "1",
      "networkMethod": null,
      "networkSource": "CHROME",
      "networkUrl": "http://www.dnslog.cn/",
      "objectType": "url",
      "parentPid": "34488",
      "parentProcessName": "explorer.exe",
      "parentProcessStartTime": "2021-12-07T13:54:39.624Z",
      "parentProcessUniqueKey": "3BB87E49FFB3FA08",
      "pid": "32264",
      "processCmd": "\"C:\\Program Files (x86)\\Google\\Chrome\\Application\\chrome.exe\"",
      "processDisplayName": "Google Chrome",
      "processGroupId": "6D902B7A48DF4C22",
      "processImagePath": "C:\\Program Files (x86)\\Google\\Chrome\\Application\\chrome.exe",
      "processImageSha1Hash": "84bc7424b07d5c3589317e5311e5ffaa60a38b62",
      "processIntegrityLevel": "MEDIUM",
      "processIsRedirectedCommandProcessor": "False",
      "processIsWow64": "False",
      "processName": "chrome.exe",
      "processRoot": "True",
      "processSessionId": "4",
      "processStartTime": "2021-12-08T13:45:34.433Z",
      "processSubSystem": "SYS_WIN32",
      "processUniqueKey": "3BB87E49FFB3FA08",
      "publisher": "GOOGLE LLC",
      "registryChangeCount": "2474",
      "relatedToThreat": "False",
      "rpid": null,
      "signatureSignedInvalidReason": null,
      "signedStatus": "signed",
      "siteId": "1018128563204802241",
      "siteName": "WinWS",
      "srcProcActiveContentFileId": null,
      "srcProcActiveContentHash": null,
      "srcProcActiveContentPath": null,
      "srcProcActiveContentSignedStatus": "unsigned",
      "srcProcActiveContentType": "FILE",
      "srcProcBinaryisExecutable": "True",
      "srcProcCmdLine": "\"C:\\Program Files (x86)\\Google\\Chrome\\Application\\chrome.exe\"",
      "srcProcDisplayName": "Google Chrome",
      "srcProcImageMd5": "1f8a0a7ed17e8f628598939dcaaa354e",
      "srcProcImagePath": "C:\\Program Files (x86)\\Google\\Chrome\\Application\\chrome.exe",
      "srcProcImageSha1": "84bc7424b07d5c3589317e5311e5ffaa60a38b62",
      "srcProcImageSha256": "196fc80802c7a409e92736de0f4c056d4d504df3ce4b0ac17ac3176b535171ed",
      "srcProcIntegrityLevel": "MEDIUM",
      "srcProcIsNative64Bit": "False",
      "srcProcIsRedirectCmdProcessor": "False",
      "srcProcIsStorylineRoot": "True",
      "srcProcName": "chrome.exe",
      "srcProcParentImageMd5": "681a21a3b848ed960073475cd77634ce",
      "srcProcParentImagePath": "C:\\WINDOWS\\explorer.exe",
      "srcProcParentImageSha1": "3d930943fbea03c9330c4947e5749ed9ceed528a",
      "srcProcParentImageSha256": "08d3f16dfbb5b5d7b419376a4f73350c13424de984fd43309160ce30bc1df089",
      "srcProcParentName": "explorer.exe",
      "srcProcParentPid": "34488",
      "srcProcParentProcUid": "48DB25F84F0FC7BE",
      "srcProcParentStartTime": "2021-12-07T13:54:39.624Z",
      "srcProcParentUid": "48DB25F84F0FC7BE",
      "srcProcPid": "32264",
      "srcProcPublisher": "GOOGLE LLC",
      "srcProcReasonSignatureInvalid": null,
      "srcProcRelatedToThreat": "False",
      "srcProcRpid": null,
      "srcProcSessionId": "4",
      "srcProcSignedStatus": "signed",
      "srcProcStartTime": "2021-12-08T13:45:34.433Z",
      "srcProcStorylineId": "6D902B7A48DF4C22",
      "srcProcSubsystem": "SYS_WIN32",
      "srcProcTid": null,
      "srcProcUid": "3BB87E49FFB3FA08",
      "srcProcUser": "AD\\Frank.Olmstead",
      "srcProcVerifiedStatus": "verified",
      "storyline": "6D902B7A48DF4C22",
      "tgtFileCreationCount": "22800",
      "tgtFileDeletionCount": "20168",
      "tgtFileModificationCount": "57178",
      "tiOriginalEventId": null,
      "tiOriginalEventIndex": null,
      "tiOriginalEventTraceId": null,
      "tid": null,
      "tiindicatorRelatedEventTime": null,
      "traceId": "01FPKXZNNF62C6NEA04A60HMB3",
      "trueContext": "6D902B7A48DF4C22",
      "url": "http://www.dnslog.cn/",
      "urlAction": null,
      "user": "AD\\Frank.Olmstead",
      "verifiedStatus": "verified"
    },
    {
      "activeContentFileId": null,
      "activeContentHash": null,
      "activeContentPath": null,
      "activeContentSignedStatus": "unsigned",
      "activeContentType": "FILE",
      "agentDomain": "AD",
      "agentGroupId": "1018129828852811657",
      "agentId": "1104551050201890355",
      "agentInfected": false,
      "agentIp": "172.31.18.165",
      "agentIsActive": true,
      "agentIsDecommissioned": false,
      "agentMachineType": "laptop",
      "agentName": "F5310-49LPXT2-L",
      "agentNetworkStatus": "connected",
      "agentOs": "windows",
      "agentTimestamp": "2021-12-11T04:59:34.468Z",
      "agentUuid": "6730bd0bd47a4a22a4a1696059ba2050",
      "agentVersion": "21.6.4.423",
      "childProcCount": "1283",
      "createdAt": "2021-12-11T04:59:34.468000Z",
      "crossProcCount": "270736",
      "crossProcDupRemoteProcHandleCount": "267329",
      "crossProcDupThreadHandleCount": "3407",
      "crossProcOpenProcCount": "0",
      "crossProcOutOfStorylineCount": "0",
      "crossProcThreadCreateCount": "0",
      "dnsCount": "0",
      "endpointMachineType": "laptop",
      "endpointName": "F5310-49LPXT2-L",
      "endpointOs": "windows",
      "eventIndex": "11",
      "eventTime": "2021-12-11T04:59:34.468Z",
      "eventType": "Not Reported",
      "fileIsExecutable": "True",
      "fileMd5": "1f8a0a7ed17e8f628598939dcaaa354e",
      "fileSha256": "196fc80802c7a409e92736de0f4c056d4d504df3ce4b0ac17ac3176b535171ed",
      "id": "631543045116919812",
      "indicatorBootConfigurationUpdateCount": "0",
      "indicatorEvasionCount": "1255",
      "indicatorExploitationCount": "152",
      "indicatorGeneralCount": "12",
      "indicatorInfostealerCount": "0",
      "indicatorInjectionCount": "0",
      "indicatorPersistenceCount": "0",
      "indicatorPostExploitationCount": "0",
      "indicatorRansomwareCount": "0",
      "indicatorReconnaissanceCount": "0",
      "metaEventName": "HTTP",
      "moduleCount": "4483",
      "netConnCount": "1",
      "netConnInCount": "0",
      "netConnOutCount": "1",
      "networkMethod": null,
      "networkSource": "CHROME",
      "networkUrl": "http://www.dnslog.cn/",
      "objectType": "url",
      "parentPid": "34488",
      "parentProcessName": "explorer.exe",
      "parentProcessStartTime": "2021-12-07T13:54:39.624Z",
      "parentProcessUniqueKey": "3BB87E49FFB3FA08",
      "pid": "32264",
      "processCmd": "\"C:\\Program Files (x86)\\Google\\Chrome\\Application\\chrome.exe\"",
      "processDisplayName": "Google Chrome",
      "processGroupId": "6D902B7A48DF4C22",
      "processImagePath": "C:\\Program Files (x86)\\Google\\Chrome\\Application\\chrome.exe",
      "processImageSha1Hash": "84bc7424b07d5c3589317e5311e5ffaa60a38b62",
      "processIntegrityLevel": "MEDIUM",
      "processIsRedirectedCommandProcessor": "False",
      "processIsWow64": "False",
      "processName": "chrome.exe",
      "processRoot": "True",
      "processSessionId": "4",
      "processStartTime": "2021-12-08T13:45:34.433Z",
      "processSubSystem": "SYS_WIN32",
      "processUniqueKey": "3BB87E49FFB3FA08",
      "publisher": "GOOGLE LLC",
      "registryChangeCount": "2459",
      "relatedToThreat": "False",
      "rpid": null,
      "signatureSignedInvalidReason": null,
      "signedStatus": "signed",
      "siteId": "1018128563204802241",
      "siteName": "WinWS",
      "srcProcActiveContentFileId": null,
      "srcProcActiveContentHash": null,
      "srcProcActiveContentPath": null,
      "srcProcActiveContentSignedStatus": "unsigned",
      "srcProcActiveContentType": "FILE",
      "srcProcBinaryisExecutable": "True",
      "srcProcCmdLine": "\"C:\\Program Files (x86)\\Google\\Chrome\\Application\\chrome.exe\"",
      "srcProcDisplayName": "Google Chrome",
      "srcProcImageMd5": "1f8a0a7ed17e8f628598939dcaaa354e",
      "srcProcImagePath": "C:\\Program Files (x86)\\Google\\Chrome\\Application\\chrome.exe",
      "srcProcImageSha1": "84bc7424b07d5c3589317e5311e5ffaa60a38b62",
      "srcProcImageSha256": "196fc80802c7a409e92736de0f4c056d4d504df3ce4b0ac17ac3176b535171ed",
      "srcProcIntegrityLevel": "MEDIUM",
      "srcProcIsNative64Bit": "False",
      "srcProcIsRedirectCmdProcessor": "False",
      "srcProcIsStorylineRoot": "True",
      "srcProcName": "chrome.exe",
      "srcProcParentImageMd5": "681a21a3b848ed960073475cd77634ce",
      "srcProcParentImagePath": "C:\\WINDOWS\\explorer.exe",
      "srcProcParentImageSha1": "3d930943fbea03c9330c4947e5749ed9ceed528a",
      "srcProcParentImageSha256": "08d3f16dfbb5b5d7b419376a4f73350c13424de984fd43309160ce30bc1df089",
      "srcProcParentName": "explorer.exe",
      "srcProcParentPid": "34488",
      "srcProcParentProcUid": "48DB25F84F0FC7BE",
      "srcProcParentStartTime": "2021-12-07T13:54:39.624Z",
      "srcProcParentUid": "48DB25F84F0FC7BE",
      "srcProcPid": "32264",
      "srcProcPublisher": "GOOGLE LLC",
      "srcProcReasonSignatureInvalid": null,
      "srcProcRelatedToThreat": "False",
      "srcProcRpid": null,
      "srcProcSessionId": "4",
      "srcProcSignedStatus": "signed",
      "srcProcStartTime": "2021-12-08T13:45:34.433Z",
      "srcProcStorylineId": "6D902B7A48DF4C22",
      "srcProcSubsystem": "SYS_WIN32",
      "srcProcTid": null,
      "srcProcUid": "3BB87E49FFB3FA08",
      "srcProcUser": "AD\\Frank.Olmstead",
      "srcProcVerifiedStatus": "verified",
      "storyline": "6D902B7A48DF4C22",
      "tgtFileCreationCount": "22712",
      "tgtFileDeletionCount": "20112",
      "tgtFileModificationCount": "56967",
      "tiOriginalEventId": null,
      "tiOriginalEventIndex": null,
      "tiOriginalEventTraceId": null,
      "tid": null,
      "tiindicatorRelatedEventTime": null,
      "traceId": "01FPKXSFXH19HERSF745X6QS3R",
      "trueContext": "6D902B7A48DF4C22",
      "url": "http://www.dnslog.cn/",
      "urlAction": null,
      "user": "AD\\Frank.Olmstead",
      "verifiedStatus": "verified"
    }
  ],
  "pagination": {
    "nextCursor": null,
    "totalItems": 10
  }
}